arriz
